package com.vorobiev.handler;

import com.vorobiev.objects.ViewRadar;

public class UpdateRadarHandler
  extends AbstractHandler
{
  ViewRadar radar;
  
  public UpdateRadarHandler(ViewRadar paramViewRadar, int paramInt)
  {
    super(paramInt);
    this.radar = paramViewRadar;
  }
  
  /* Error */
  public void update(android.os.Message paramMessage)
  {
    // Byte code:
    //   0: iconst_0
    //   1: istore_2
    //   2: getstatic 22	com/vorobiev/data/RadarData:radarColor	[I
    //   5: astore 5
    //   7: aload 5
    //   9: monitorenter
    //   10: bipush 97
    //   12: istore_3
    //   13: iload_3
    //   14: iconst_m1
    //   15: if_icmpgt +14 -> 29
    //   18: aload 5
    //   20: monitorexit
    //   21: aload_0
    //   22: getfield 13	com/vorobiev/handler/UpdateRadarHandler:radar	Lcom/vorobiev/objects/ViewRadar;
    //   25: invokevirtual 28	com/vorobiev/objects/ViewRadar:invalidate	()V
    //   28: return
    //   29: iconst_0
    //   30: istore 4
    //   32: iload 4
    //   34: sipush 147
    //   37: if_icmplt +10 -> 47
    //   40: iload_3
    //   41: iconst_1
    //   42: isub
    //   43: istore_3
    //   44: goto -31 -> 13
    //   47: getstatic 32	com/vorobiev/data/RadarData:mapRadar	Landroid/graphics/Bitmap;
    //   50: astore_1
    //   51: getstatic 22	com/vorobiev/data/RadarData:radarColor	[I
    //   54: astore 6
    //   56: aload_1
    //   57: iload 4
    //   59: iload_3
    //   60: aload 6
    //   62: iload_2
    //   63: iaload
    //   64: invokevirtual 38	android/graphics/Bitmap:setPixel	(III)V
    //   67: iload 4
    //   69: iconst_1
    //   70: iadd
    //   71: istore 4
    //   73: iload_2
    //   74: iconst_1
    //   75: iadd
    //   76: istore_2
    //   77: goto -45 -> 32
    //   80: aload 5
    //   82: monitorexit
    //   83: aload_1
    //   84: athrow
    //   85: astore_1
    //   86: goto -6 -> 80
    //   89: astore_1
    //   90: goto -10 -> 80
    // Local variable table:
    //   start	length	slot	name	signature
    //   0	93	0	this	UpdateRadarHandler
    //   0	93	1	paramMessage	android.os.Message
    //   1	76	2	i	int
    //   12	48	3	j	int
    //   30	42	4	k	int
    //   5	76	5	arrayOfInt1	int[]
    //   54	7	6	arrayOfInt2	int[]
    // Exception table:
    //   from	to	target	type
    //   18	21	85	finally
    //   56	67	85	finally
    //   80	83	85	finally
    //   47	56	89	finally
  }
}


/* Location:              C:\Users\Сергей\Desktop\SK35-dex2jar.jar!\com\vorobiev\handler\UpdateRadarHandler.class
 * Java compiler version: 6 (50.0)
 * JD-Core Version:       0.7.1
 */